vaultix/__init__.py
vaultix/__main__.py
vaultix/config.py
vaultix/constants.py
vaultix/core.py
vaultix/ssh_agent.py
vaultix/utils.py
vaultix/cli/__init__.py
vaultix/cli/add_cmd.py
vaultix/cli/agent_cmd.py
vaultix/cli/base.py
vaultix/cli/check_cmd.py
vaultix/cli/config_cmd.py
vaultix/cli/connect_cmd.py
vaultix/cli/copy_cmd.py
vaultix/cli/delete_cmd.py
vaultix/cli/edit_cmd.py
vaultix/cli/exec_cmd.py
vaultix/cli/export_cmd.py
vaultix/cli/import_cmd.py
vaultix/cli/list_cmd.py
vaultix/cli/rename_cmd.py
vaultix/cli/search_cmd.py
vaultix/cli/show_cmd.py
vaultix_ssh-1.0.1.dist-info/licenses/LICENSE
vaultix_ssh-1.0.1.dist-info/METADATA
vaultix_ssh-1.0.1.dist-info/WHEEL
vaultix_ssh-1.0.1.dist-info/entry_points.txt
vaultix_ssh-1.0.1.dist-info/top_level.txt
vaultix_ssh-1.0.1.dist-info/RECORD
