Metadata-Version: 2.4
Name: vaultix-ssh
Version: 1.0.1
Summary: A modern SSH connection manager with built-in agent support
Home-page: https://github.com/Tusharmohanpuria/Vaultix-SSH
Author: tusharmohanpuria1711@gmail.com
Author-email: 
Classifier: Programming Language :: Python :: 3
Classifier: License :: OSI Approved :: MIT License
Classifier: Operating System :: OS Independent
Classifier: Environment :: Console
Classifier: Topic :: System :: Systems Administration
Classifier: Topic :: Utilities
Requires-Python: >=3.6
License-File: LICENSE
Requires-Dist: click>=8.0.0
Requires-Dist: rich>=10.0.0
Requires-Dist: pycryptodome>=3.15.0
Requires-Dist: appdirs>=1.4.4
Dynamic: author
Dynamic: classifier
Dynamic: description
Dynamic: description-content-type
Dynamic: home-page
Dynamic: license-file
Dynamic: requires-dist
Dynamic: requires-python
Dynamic: summary
